{"products":[{"id":940400,"key":"00mj149","parent_key":"","name":"1.2TB [00MJ149]","full_name":"Lenovo 1.2TB [00MJ149]","name_prefix":"Жесткий диск","extended_name":"Жесткий диск Lenovo 1.2TB [00MJ149]","status":"active","images":{"header":"https:\/\/imgproxy.onliner.by\/4Yb-jtP3yI_8o3d-LDB8u5e0IKlnn-q6gO0S7ysy7lM\/w:170\/h:250\/z:2\/f:jpg\/aHR0cHM6Ly9jb250\/ZW50Lm9ubGluZXIu\/YnkvY2F0YWxvZy9k\/ZXZpY2Uvb3JpZ2lu\/YWwvYjM2NDI3NDli\/NGI5ZWI5ZTNiNTFh\/MTFiNmU1NTU2MjEu\/anBlZw"},"description":"2.5\", SAS 2.0 (6Gbps), 10000 об\/мин, буфер 32 МБ, время доступа 2.8 мс","description_list":["2.5\"","SAS 2.0 (6Gbps)","10000 об\/мин","буфер 32 МБ","время доступа 2.8 мс"],"micro_description":"2.5\", SAS 2.0 (6Gbps), 10000 об\/мин, буфер 32 МБ","micro_description_list":["2.5\"","SAS 2.0 (6Gbps)","10000 об\/мин","буфер 32 МБ"],"html_url":"https:\/\/catalog.onliner.by\/hdd\/lenovo\/00mj149","reviews":{"rating":0,"count":0,"html_url":"https:\/\/catalog.onliner.by\/hdd\/lenovo\/00mj149\/reviews","url":"https:\/\/catalog.api.onliner.by\/products\/00mj149\/reviews"},"review_url":null,"color_code":null,"prices":{"price_min":{"amount":"1870.75","currency":"BYN","converted":{"BYN":{"amount":"1870.75","currency":"BYN"}}},"price_max":{"amount":"1870.75","currency":"BYN","converted":{"BYN":{"amount":"1870.75","currency":"BYN"}}},"offers":{"count":2},"html_url":"https:\/\/catalog.onliner.by\/hdd\/lenovo\/00mj149\/prices","url":"https:\/\/shop.api.onliner.by\/products\/00mj149\/positions"},"max_installment_terms":null,"max_cobrand_cashback":null,"sale":{"is_on_sale":false,"discount":0,"min_prices_median":{"amount":"1810.91","currency":"BYN"},"subscribed":false,"can_be_subscribed":true},"second":{"offers_count":0,"min_price":null,"max_price":null},"forum":{"topic_id":null,"topic_url":null,"post_url":"https:\/\/forum.onliner.by\/posting.php?mode=newtopic&f=148&device=00mj149","replies_count":null},"url":"https:\/\/catalog.api.onliner.by\/products\/00mj149","advertise":null,"stickers":null,"prime_info":{"available":false},"in_bookmarks":false,"by_parts_info":null},{"id":940372,"key":"00wg685","parent_key":"","name":"300GB [00WG685]","full_name":"Lenovo 300GB [00WG685]","name_prefix":"Жесткий диск","extended_name":"Жесткий диск Lenovo 300GB [00WG685]","status":"active","images":{"header":"https:\/\/imgproxy.onliner.by\/Fu-9MsMT0ne_G6jwhnQk2pkCeFf5YnxlYraRRS9Xgmk\/w:170\/h:250\/z:2\/f:jpg\/aHR0cHM6Ly9jb250\/ZW50Lm9ubGluZXIu\/YnkvY2F0YWxvZy9k\/ZXZpY2Uvb3JpZ2lu\/YWwvMjc2MzNlNjI2\/MGFmMjMwNWMwYzE5\/ZjQ1NzdlMTMxYjIu\/anBlZw"},"description":"2.5\", SAS 3.0 (12Gbps), 10000 об\/мин","description_list":["2.5\"","SAS 3.0 (12Gbps)","10000 об\/мин"],"micro_description":"2.5\", SAS 3.0 (12Gbps), 10000 об\/мин","micro_description_list":["2.5\"","SAS 3.0 (12Gbps)","10000 об\/мин"],"html_url":"https:\/\/catalog.onliner.by\/hdd\/lenovo\/00wg685","reviews":{"rating":0,"count":0,"html_url":"https:\/\/catalog.onliner.by\/hdd\/lenovo\/00wg685\/reviews","url":"https:\/\/catalog.api.onliner.by\/products\/00wg685\/reviews"},"review_url":null,"color_code":null,"prices":{"price_min":{"amount":"821.00","currency":"BYN","converted":{"BYN":{"amount":"821.00","currency":"BYN"}}},"price_max":{"amount":"821.80","currency":"BYN","converted":{"BYN":{"amount":"821.80","currency":"BYN"}}},"offers":{"count":3},"html_url":"https:\/\/catalog.onliner.by\/hdd\/lenovo\/00wg685\/prices","url":"https:\/\/shop.api.onliner.by\/products\/00wg685\/positions"},"max_installment_terms":null,"max_cobrand_cashback":null,"sale":{"is_on_sale":false,"discount":0,"min_prices_median":{"amount":"829.00","currency":"BYN"},"subscribed":false,"can_be_subscribed":true},"second":{"offers_count":0,"min_price":null,"max_price":null},"forum":{"topic_id":null,"topic_url":null,"post_url":"https:\/\/forum.onliner.by\/posting.php?mode=newtopic&f=148&device=00wg685","replies_count":null},"url":"https:\/\/catalog.api.onliner.by\/products\/00wg685","advertise":null,"stickers":null,"prime_info":{"available":false},"in_bookmarks":false,"by_parts_info":null},{"id":940367,"key":"81y9650","parent_key":"","name":"900GB [81Y9650]","full_name":"Lenovo 900GB [81Y9650]","name_prefix":"Жесткий диск","extended_name":"Жесткий диск Lenovo 900GB [81Y9650]","status":"active","images":{"header":"https:\/\/imgproxy.onliner.by\/4Yb-jtP3yI_8o3d-LDB8u5e0IKlnn-q6gO0S7ysy7lM\/w:170\/h:250\/z:2\/f:jpg\/aHR0cHM6Ly9jb250\/ZW50Lm9ubGluZXIu\/YnkvY2F0YWxvZy9k\/ZXZpY2Uvb3JpZ2lu\/YWwvYjM2NDI3NDli\/NGI5ZWI5ZTNiNTFh\/MTFiNmU1NTU2MjEu\/anBlZw"},"description":"2.5\", SAS 2.0 (6Gbps), 10000 об\/мин, буфер 16 МБ","description_list":["2.5\"","SAS 2.0 (6Gbps)","10000 об\/мин","буфер 16 МБ"],"micro_description":"2.5\", SAS 2.0 (6Gbps), 10000 об\/мин, буфер 16 МБ","micro_description_list":["2.5\"","SAS 2.0 (6Gbps)","10000 об\/мин","буфер 16 МБ"],"html_url":"https:\/\/catalog.onliner.by\/hdd\/lenovo\/81y9650","reviews":{"rating":0,"count":0,"html_url":"https:\/\/catalog.onliner.by\/hdd\/lenovo\/81y9650\/reviews","url":"https:\/\/catalog.api.onliner.by\/products\/81y9650\/reviews"},"review_url":null,"color_code":null,"prices":{"price_min":{"amount":"552.85","currency":"BYN","converted":{"BYN":{"amount":"552.85","currency":"BYN"}}},"price_max":{"amount":"552.85","currency":"BYN","converted":{"BYN":{"amount":"552.85","currency":"BYN"}}},"offers":{"count":1},"html_url":"https:\/\/catalog.onliner.by\/hdd\/lenovo\/81y9650\/prices","url":"https:\/\/shop.api.onliner.by\/products\/81y9650\/positions"},"max_installment_terms":null,"max_cobrand_cashback":null,"sale":{"is_on_sale":false,"discount":0,"min_prices_median":{"amount":"987.70","currency":"BYN"},"subscribed":false,"can_be_subscribed":true},"second":{"offers_count":0,"min_price":null,"max_price":null},"forum":{"topic_id":null,"topic_url":null,"post_url":"https:\/\/forum.onliner.by\/posting.php?mode=newtopic&f=148&device=81y9650","replies_count":null},"url":"https:\/\/catalog.api.onliner.by\/products\/81y9650","advertise":null,"stickers":null,"prime_info":{"available":false},"in_bookmarks":false,"by_parts_info":null},{"id":940365,"key":"90y8872","parent_key":"","name":"90Y8872 600GB","full_name":"Lenovo 90Y8872 600GB","name_prefix":"Жесткий диск","extended_name":"Жесткий диск Lenovo 90Y8872 600GB","status":"active","images":{"header":"https:\/\/imgproxy.onliner.by\/Fu-9MsMT0ne_G6jwhnQk2pkCeFf5YnxlYraRRS9Xgmk\/w:170\/h:250\/z:2\/f:jpg\/aHR0cHM6Ly9jb250\/ZW50Lm9ubGluZXIu\/YnkvY2F0YWxvZy9k\/ZXZpY2Uvb3JpZ2lu\/YWwvMjc2MzNlNjI2\/MGFmMjMwNWMwYzE5\/ZjQ1NzdlMTMxYjIu\/anBlZw"},"description":"2.5\", SAS 1.0 (3Gbps), 10000 об\/мин, буфер 16 МБ","description_list":["2.5\"","SAS 1.0 (3Gbps)","10000 об\/мин","буфер 16 МБ"],"micro_description":"2.5\", SAS 1.0 (3Gbps), 10000 об\/мин, буфер 16 МБ","micro_description_list":["2.5\"","SAS 1.0 (3Gbps)","10000 об\/мин","буфер 16 МБ"],"html_url":"https:\/\/catalog.onliner.by\/hdd\/lenovo\/90y8872","reviews":{"rating":0,"count":0,"html_url":"https:\/\/catalog.onliner.by\/hdd\/lenovo\/90y8872\/reviews","url":"https:\/\/catalog.api.onliner.by\/products\/90y8872\/reviews"},"review_url":null,"color_code":null,"prices":{"price_min":{"amount":"559.90","currency":"BYN","converted":{"BYN":{"amount":"559.90","currency":"BYN"}}},"price_max":{"amount":"926.56","currency":"BYN","converted":{"BYN":{"amount":"926.56","currency":"BYN"}}},"offers":{"count":3},"html_url":"https:\/\/catalog.onliner.by\/hdd\/lenovo\/90y8872\/prices","url":"https:\/\/shop.api.onliner.by\/products\/90y8872\/positions"},"max_installment_terms":null,"max_cobrand_cashback":null,"sale":{"is_on_sale":false,"discount":0,"min_prices_median":{"amount":"559.90","currency":"BYN"},"subscribed":false,"can_be_subscribed":true},"second":{"offers_count":0,"min_price":null,"max_price":null},"forum":{"topic_id":null,"topic_url":null,"post_url":"https:\/\/forum.onliner.by\/posting.php?mode=newtopic&f=148&device=90y8872","replies_count":null},"url":"https:\/\/catalog.api.onliner.by\/products\/90y8872","advertise":null,"stickers":null,"prime_info":{"available":false},"in_bookmarks":false,"by_parts_info":null},{"id":940328,"key":"400ajpp","parent_key":"","name":"600GB [400-AJPP]","full_name":"Dell 600GB [400-AJPP]","name_prefix":"Жесткий диск","extended_name":"Жесткий диск Dell 600GB [400-AJPP]","status":"active","images":{"header":"https:\/\/imgproxy.onliner.by\/ni7JfcmY2s0AYU0h-IU1pQCkem3NguUlBzz2K3RnkUE\/w:170\/h:250\/z:2\/f:jpg\/aHR0cHM6Ly9jb250\/ZW50Lm9ubGluZXIu\/YnkvY2F0YWxvZy9k\/ZXZpY2Uvb3JpZ2lu\/YWwvYWVhOTU2NTZl\/NzhmZDY5NTQ0MWRm\/M2UyMmRlZmFjOWUu\/anBlZw"},"description":"2.5\", SAS 2.0 (6Gbps), 10000 об\/мин, буфер 16 МБ","description_list":["2.5\"","SAS 2.0 (6Gbps)","10000 об\/мин","буфер 16 МБ"],"micro_description":"2.5\", SAS 2.0 (6Gbps), 10000 об\/мин, буфер 16 МБ","micro_description_list":["2.5\"","SAS 2.0 (6Gbps)","10000 об\/мин","буфер 16 МБ"],"html_url":"https:\/\/catalog.onliner.by\/hdd\/dell\/400ajpp","reviews":{"rating":0,"count":0,"html_url":"https:\/\/catalog.onliner.by\/hdd\/dell\/400ajpp\/reviews","url":"https:\/\/catalog.api.onliner.by\/products\/400ajpp\/reviews"},"review_url":null,"color_code":null,"prices":{"price_min":{"amount":"870.49","currency":"BYN","converted":{"BYN":{"amount":"870.49","currency":"BYN"}}},"price_max":{"amount":"870.49","currency":"BYN","converted":{"BYN":{"amount":"870.49","currency":"BYN"}}},"offers":{"count":2},"html_url":"https:\/\/catalog.onliner.by\/hdd\/dell\/400ajpp\/prices","url":"https:\/\/shop.api.onliner.by\/products\/400ajpp\/positions"},"max_installment_terms":null,"max_cobrand_cashback":null,"sale":{"is_on_sale":false,"discount":0,"min_prices_median":{"amount":"774.22","currency":"BYN"},"subscribed":false,"can_be_subscribed":true},"second":{"offers_count":0,"min_price":null,"max_price":null},"forum":{"topic_id":null,"topic_url":null,"post_url":"https:\/\/forum.onliner.by\/posting.php?mode=newtopic&f=148&device=400ajpp","replies_count":null},"url":"https:\/\/catalog.api.onliner.by\/products\/400ajpp","advertise":null,"stickers":null,"prime_info":{"available":false},"in_bookmarks":false,"by_parts_info":null},{"id":940215,"key":"400ajph","parent_key":"","name":"600GB [400-AJPH]","full_name":"Dell 600GB [400-AJPH]","name_prefix":"Жесткий диск","extended_name":"Жесткий диск Dell 600GB [400-AJPH]","status":"active","images":{"header":"https:\/\/imgproxy.onliner.by\/ni7JfcmY2s0AYU0h-IU1pQCkem3NguUlBzz2K3RnkUE\/w:170\/h:250\/z:2\/f:jpg\/aHR0cHM6Ly9jb250\/ZW50Lm9ubGluZXIu\/YnkvY2F0YWxvZy9k\/ZXZpY2Uvb3JpZ2lu\/YWwvYWVhOTU2NTZl\/NzhmZDY5NTQ0MWRm\/M2UyMmRlZmFjOWUu\/anBlZw"},"description":"2.5\", SAS 3.0 (12Gbps), 10000 об\/мин, буфер 16 МБ, время доступа 2.9 мс","description_list":["2.5\"","SAS 3.0 (12Gbps)","10000 об\/мин","буфер 16 МБ","время доступа 2.9 мс"],"micro_description":"2.5\", SAS 3.0 (12Gbps), 10000 об\/мин, буфер 16 МБ","micro_description_list":["2.5\"","SAS 3.0 (12Gbps)","10000 об\/мин","буфер 16 МБ"],"html_url":"https:\/\/catalog.onliner.by\/hdd\/dell\/400ajph","reviews":{"rating":0,"count":0,"html_url":"https:\/\/catalog.onliner.by\/hdd\/dell\/400ajph\/reviews","url":"https:\/\/catalog.api.onliner.by\/products\/400ajph\/reviews"},"review_url":null,"color_code":null,"prices":{"price_min":{"amount":"1294.00","currency":"BYN","converted":{"BYN":{"amount":"1294.00","currency":"BYN"}}},"price_max":{"amount":"1294.00","currency":"BYN","converted":{"BYN":{"amount":"1294.00","currency":"BYN"}}},"offers":{"count":3},"html_url":"https:\/\/catalog.onliner.by\/hdd\/dell\/400ajph\/prices","url":"https:\/\/shop.api.onliner.by\/products\/400ajph\/positions"},"max_installment_terms":null,"max_cobrand_cashback":null,"sale":{"is_on_sale":false,"discount":0,"min_prices_median":{"amount":"1176.00","currency":"BYN"},"subscribed":false,"can_be_subscribed":true},"second":{"offers_count":0,"min_price":null,"max_price":null},"forum":{"topic_id":null,"topic_url":null,"post_url":"https:\/\/forum.onliner.by\/posting.php?mode=newtopic&f=148&device=400ajph","replies_count":null},"url":"https:\/\/catalog.api.onliner.by\/products\/400ajph","advertise":null,"stickers":null,"prime_info":{"available":false},"in_bookmarks":false,"by_parts_info":null},{"id":940186,"key":"781516b21","parent_key":"","name":"781516-B21 600GB","full_name":"HP 781516-B21 600GB","name_prefix":"Жесткий диск","extended_name":"Жесткий диск HP 781516-B21 600GB","status":"active","images":{"header":"https:\/\/imgproxy.onliner.by\/EilV5gTaPJJ7EUAiiWHbO_VbenKYwu0dMVz__iT0Hic\/w:170\/h:250\/z:2\/f:jpg\/aHR0cHM6Ly9jb250\/ZW50Lm9ubGluZXIu\/YnkvY2F0YWxvZy9k\/ZXZpY2Uvb3JpZ2lu\/YWwvYzRlMGJlYWI0\/ODY1ZGRjYzc1NmNh\/YTM2YzY1Y2I2ZGEu\/anBlZw"},"description":"2.5\", SAS 3.0 (12Gbps), 10000 об\/мин","description_list":["2.5\"","SAS 3.0 (12Gbps)","10000 об\/мин"],"micro_description":"2.5\", SAS 3.0 (12Gbps), 10000 об\/мин","micro_description_list":["2.5\"","SAS 3.0 (12Gbps)","10000 об\/мин"],"html_url":"https:\/\/catalog.onliner.by\/hdd\/hp\/781516b21","reviews":{"rating":0,"count":0,"html_url":"https:\/\/catalog.onliner.by\/hdd\/hp\/781516b21\/reviews","url":"https:\/\/catalog.api.onliner.by\/products\/781516b21\/reviews"},"review_url":null,"color_code":null,"prices":{"price_min":{"amount":"716.32","currency":"BYN","converted":{"BYN":{"amount":"716.32","currency":"BYN"}}},"price_max":{"amount":"982.63","currency":"BYN","converted":{"BYN":{"amount":"982.63","currency":"BYN"}}},"offers":{"count":3},"html_url":"https:\/\/catalog.onliner.by\/hdd\/hp\/781516b21\/prices","url":"https:\/\/shop.api.onliner.by\/products\/781516b21\/positions"},"max_installment_terms":null,"max_cobrand_cashback":null,"sale":{"is_on_sale":false,"discount":0,"min_prices_median":{"amount":"716.32","currency":"BYN"},"subscribed":false,"can_be_subscribed":true},"second":{"offers_count":0,"min_price":null,"max_price":null},"forum":{"topic_id":null,"topic_url":null,"post_url":"https:\/\/forum.onliner.by\/posting.php?mode=newtopic&f=148&device=781516b21","replies_count":null},"url":"https:\/\/catalog.api.onliner.by\/products\/781516b21","advertise":null,"stickers":null,"prime_info":{"available":false},"in_bookmarks":false,"by_parts_info":null},{"id":940185,"key":"j9f47a","parent_key":"","name":"900GB [J9F47A]","full_name":"HP 900GB [J9F47A]","name_prefix":"Жесткий диск","extended_name":"Жесткий диск HP 900GB [J9F47A]","status":"active","images":{"header":"https:\/\/imgproxy.onliner.by\/EilV5gTaPJJ7EUAiiWHbO_VbenKYwu0dMVz__iT0Hic\/w:170\/h:250\/z:2\/f:jpg\/aHR0cHM6Ly9jb250\/ZW50Lm9ubGluZXIu\/YnkvY2F0YWxvZy9k\/ZXZpY2Uvb3JpZ2lu\/YWwvYzRlMGJlYWI0\/ODY1ZGRjYzc1NmNh\/YTM2YzY1Y2I2ZGEu\/anBlZw"},"description":"2.5\", SAS 3.0 (12Gbps), 10000 об\/мин","description_list":["2.5\"","SAS 3.0 (12Gbps)","10000 об\/мин"],"micro_description":"2.5\", SAS 3.0 (12Gbps), 10000 об\/мин","micro_description_list":["2.5\"","SAS 3.0 (12Gbps)","10000 об\/мин"],"html_url":"https:\/\/catalog.onliner.by\/hdd\/hp\/j9f47a","reviews":{"rating":0,"count":0,"html_url":"https:\/\/catalog.onliner.by\/hdd\/hp\/j9f47a\/reviews","url":"https:\/\/catalog.api.onliner.by\/products\/j9f47a\/reviews"},"review_url":null,"color_code":null,"prices":{"price_min":{"amount":"1059.00","currency":"BYN","converted":{"BYN":{"amount":"1059.00","currency":"BYN"}}},"price_max":{"amount":"1200.72","currency":"BYN","converted":{"BYN":{"amount":"1200.72","currency":"BYN"}}},"offers":{"count":4},"html_url":"https:\/\/catalog.onliner.by\/hdd\/hp\/j9f47a\/prices","url":"https:\/\/shop.api.onliner.by\/products\/j9f47a\/positions"},"max_installment_terms":null,"max_cobrand_cashback":null,"sale":{"is_on_sale":false,"discount":0,"min_prices_median":{"amount":"1059.00","currency":"BYN"},"subscribed":false,"can_be_subscribed":true},"second":{"offers_count":0,"min_price":null,"max_price":null},"forum":{"topic_id":null,"topic_url":null,"post_url":"https:\/\/forum.onliner.by\/posting.php?mode=newtopic&f=148&device=j9f47a","replies_count":null},"url":"https:\/\/catalog.api.onliner.by\/products\/j9f47a","advertise":null,"stickers":null,"prime_info":{"available":false},"in_bookmarks":false,"by_parts_info":null},{"id":940155,"key":"n9x93a","parent_key":"","name":"2TB [N9X93A]","full_name":"HP 2TB [N9X93A]","name_prefix":"Жесткий диск","extended_name":"Жесткий диск HP 2TB [N9X93A]","status":"active","images":{"header":"https:\/\/imgproxy.onliner.by\/o99y86b87Apw-KhdpaBjLVDiKHYhKtq22V8HGw2Nfbw\/w:170\/h:250\/z:2\/f:jpg\/aHR0cHM6Ly9jb250\/ZW50Lm9ubGluZXIu\/YnkvY2F0YWxvZy9k\/ZXZpY2Uvb3JpZ2lu\/YWwvNDAyOWRjYzBl\/NzMwNjFkOGQ3OGFl\/NDBmOGRmM2RiMTMu\/cG5n"},"description":"3.5\", SAS 3.0 (12Gbps), 7200 об\/мин","description_list":["3.5\"","SAS 3.0 (12Gbps)","7200 об\/мин"],"micro_description":"3.5\", SAS 3.0 (12Gbps), 7200 об\/мин","micro_description_list":["3.5\"","SAS 3.0 (12Gbps)","7200 об\/мин"],"html_url":"https:\/\/catalog.onliner.by\/hdd\/hp\/n9x93a","reviews":{"rating":0,"count":0,"html_url":"https:\/\/catalog.onliner.by\/hdd\/hp\/n9x93a\/reviews","url":"https:\/\/catalog.api.onliner.by\/products\/n9x93a\/reviews"},"review_url":null,"color_code":null,"prices":{"price_min":{"amount":"1886.30","currency":"BYN","converted":{"BYN":{"amount":"1886.30","currency":"BYN"}}},"price_max":{"amount":"1886.30","currency":"BYN","converted":{"BYN":{"amount":"1886.30","currency":"BYN"}}},"offers":{"count":1},"html_url":"https:\/\/catalog.onliner.by\/hdd\/hp\/n9x93a\/prices","url":"https:\/\/shop.api.onliner.by\/products\/n9x93a\/positions"},"max_installment_terms":null,"max_cobrand_cashback":null,"sale":{"is_on_sale":false,"discount":0,"min_prices_median":{"amount":"1537.00","currency":"BYN"},"subscribed":false,"can_be_subscribed":true},"second":{"offers_count":0,"min_price":null,"max_price":null},"forum":{"topic_id":null,"topic_url":null,"post_url":"https:\/\/forum.onliner.by\/posting.php?mode=newtopic&f=148&device=n9x93a","replies_count":null},"url":"https:\/\/catalog.api.onliner.by\/products\/n9x93a","advertise":null,"stickers":null,"prime_info":{"available":false},"in_bookmarks":false,"by_parts_info":null},{"id":940152,"key":"801884b21","parent_key":"","name":"2TB [801884-B21]","full_name":"HP 2TB [801884-B21]","name_prefix":"Жесткий диск","extended_name":"Жесткий диск HP 2TB [801884-B21]","status":"active","images":{"header":"https:\/\/imgproxy.onliner.by\/9szIZoaypducBk_PWNLauK4sjmJ3e1KuH70s4sgTJrU\/w:170\/h:250\/z:2\/f:jpg\/aHR0cHM6Ly9jb250\/ZW50Lm9ubGluZXIu\/YnkvY2F0YWxvZy9k\/ZXZpY2Uvb3JpZ2lu\/YWwvMzkzZTVhOTQ2\/NmJjNGM2N2ExMTQz\/Mjk0MDgwNGM0ZGQu\/cG5n"},"description":"3.5\", SATA 3.0 (6Gbps), 7200 об\/мин","description_list":["3.5\"","SATA 3.0 (6Gbps)","7200 об\/мин"],"micro_description":"3.5\", SATA 3.0 (6Gbps), 7200 об\/мин","micro_description_list":["3.5\"","SATA 3.0 (6Gbps)","7200 об\/мин"],"html_url":"https:\/\/catalog.onliner.by\/hdd\/hp\/801884b21","reviews":{"rating":0,"count":0,"html_url":"https:\/\/catalog.onliner.by\/hdd\/hp\/801884b21\/reviews","url":"https:\/\/catalog.api.onliner.by\/products\/801884b21\/reviews"},"review_url":null,"color_code":null,"prices":{"price_min":{"amount":"1087.00","currency":"BYN","converted":{"BYN":{"amount":"1087.00","currency":"BYN"}}},"price_max":{"amount":"1087.00","currency":"BYN","converted":{"BYN":{"amount":"1087.00","currency":"BYN"}}},"offers":{"count":1},"html_url":"https:\/\/catalog.onliner.by\/hdd\/hp\/801884b21\/prices","url":"https:\/\/shop.api.onliner.by\/products\/801884b21\/positions"},"max_installment_terms":null,"max_cobrand_cashback":null,"sale":{"is_on_sale":false,"discount":0,"min_prices_median":{"amount":"987.00","currency":"BYN"},"subscribed":false,"can_be_subscribed":true},"second":{"offers_count":0,"min_price":null,"max_price":null},"forum":{"topic_id":null,"topic_url":null,"post_url":"https:\/\/forum.onliner.by\/posting.php?mode=newtopic&f=148&device=801884b21","replies_count":null},"url":"https:\/\/catalog.api.onliner.by\/products\/801884b21","advertise":null,"stickers":null,"prime_info":{"available":false},"in_bookmarks":false,"by_parts_info":null},{"id":940149,"key":"qk703a","parent_key":"","name":"3TB QK703A","full_name":"HP 3TB QK703A","name_prefix":"Жесткий диск","extended_name":"Жесткий диск HP 3TB QK703A","status":"active","images":{"header":"https:\/\/imgproxy.onliner.by\/o99y86b87Apw-KhdpaBjLVDiKHYhKtq22V8HGw2Nfbw\/w:170\/h:250\/z:2\/f:jpg\/aHR0cHM6Ly9jb250\/ZW50Lm9ubGluZXIu\/YnkvY2F0YWxvZy9k\/ZXZpY2Uvb3JpZ2lu\/YWwvNDAyOWRjYzBl\/NzMwNjFkOGQ3OGFl\/NDBmOGRmM2RiMTMu\/cG5n"},"description":"3.5\", SAS 2.0 (6Gbps), 7200 об\/мин","description_list":["3.5\"","SAS 2.0 (6Gbps)","7200 об\/мин"],"micro_description":"3.5\", SAS 2.0 (6Gbps), 7200 об\/мин","micro_description_list":["3.5\"","SAS 2.0 (6Gbps)","7200 об\/мин"],"html_url":"https:\/\/catalog.onliner.by\/hdd\/hp\/qk703a","reviews":{"rating":0,"count":0,"html_url":"https:\/\/catalog.onliner.by\/hdd\/hp\/qk703a\/reviews","url":"https:\/\/catalog.api.onliner.by\/products\/qk703a\/reviews"},"review_url":null,"color_code":null,"prices":{"price_min":{"amount":"802.60","currency":"BYN","converted":{"BYN":{"amount":"802.60","currency":"BYN"}}},"price_max":{"amount":"1971.23","currency":"BYN","converted":{"BYN":{"amount":"1971.23","currency":"BYN"}}},"offers":{"count":3},"html_url":"https:\/\/catalog.onliner.by\/hdd\/hp\/qk703a\/prices","url":"https:\/\/shop.api.onliner.by\/products\/qk703a\/positions"},"max_installment_terms":null,"max_cobrand_cashback":null,"sale":{"is_on_sale":false,"discount":0,"min_prices_median":{"amount":"802.60","currency":"BYN"},"subscribed":false,"can_be_subscribed":true},"second":{"offers_count":0,"min_price":null,"max_price":null},"forum":{"topic_id":null,"topic_url":null,"post_url":"https:\/\/forum.onliner.by\/posting.php?mode=newtopic&f=148&device=qk703a","replies_count":null},"url":"https:\/\/catalog.api.onliner.by\/products\/qk703a","advertise":null,"stickers":null,"prime_info":{"available":false},"in_bookmarks":false,"by_parts_info":null},{"id":940144,"key":"qr496a","parent_key":"","name":"900GB QR496A","full_name":"HP 900GB QR496A","name_prefix":"Жесткий диск","extended_name":"Жесткий диск HP 900GB QR496A","status":"active","images":{"header":"https:\/\/imgproxy.onliner.by\/EilV5gTaPJJ7EUAiiWHbO_VbenKYwu0dMVz__iT0Hic\/w:170\/h:250\/z:2\/f:jpg\/aHR0cHM6Ly9jb250\/ZW50Lm9ubGluZXIu\/YnkvY2F0YWxvZy9k\/ZXZpY2Uvb3JpZ2lu\/YWwvYzRlMGJlYWI0\/ODY1ZGRjYzc1NmNh\/YTM2YzY1Y2I2ZGEu\/anBlZw"},"description":"2.5\", SAS 2.0 (6Gbps), 10000 об\/мин","description_list":["2.5\"","SAS 2.0 (6Gbps)","10000 об\/мин"],"micro_description":"2.5\", SAS 2.0 (6Gbps), 10000 об\/мин","micro_description_list":["2.5\"","SAS 2.0 (6Gbps)","10000 об\/мин"],"html_url":"https:\/\/catalog.onliner.by\/hdd\/hp\/qr496a","reviews":{"rating":0,"count":0,"html_url":"https:\/\/catalog.onliner.by\/hdd\/hp\/qr496a\/reviews","url":"https:\/\/catalog.api.onliner.by\/products\/qr496a\/reviews"},"review_url":null,"color_code":null,"prices":{"price_min":{"amount":"667.50","currency":"BYN","converted":{"BYN":{"amount":"667.50","currency":"BYN"}}},"price_max":{"amount":"667.50","currency":"BYN","converted":{"BYN":{"amount":"667.50","currency":"BYN"}}},"offers":{"count":1},"html_url":"https:\/\/catalog.onliner.by\/hdd\/hp\/qr496a\/prices","url":"https:\/\/shop.api.onliner.by\/products\/qr496a\/positions"},"max_installment_terms":null,"max_cobrand_cashback":null,"sale":{"is_on_sale":false,"discount":0,"min_prices_median":{"amount":"0.00","currency":"BYN"},"subscribed":false,"can_be_subscribed":true},"second":{"offers_count":0,"min_price":null,"max_price":null},"forum":{"topic_id":null,"topic_url":null,"post_url":"https:\/\/forum.onliner.by\/posting.php?mode=newtopic&f=148&device=qr496a","replies_count":null},"url":"https:\/\/catalog.api.onliner.by\/products\/qr496a","advertise":null,"stickers":null,"prime_info":{"available":false},"in_bookmarks":false,"by_parts_info":null},{"id":940140,"key":"qr492a","parent_key":"","name":"300GB QR492A","full_name":"HP 300GB QR492A","name_prefix":"Жесткий диск","extended_name":"Жесткий диск HP 300GB QR492A","status":"active","images":{"header":"https:\/\/imgproxy.onliner.by\/EilV5gTaPJJ7EUAiiWHbO_VbenKYwu0dMVz__iT0Hic\/w:170\/h:250\/z:2\/f:jpg\/aHR0cHM6Ly9jb250\/ZW50Lm9ubGluZXIu\/YnkvY2F0YWxvZy9k\/ZXZpY2Uvb3JpZ2lu\/YWwvYzRlMGJlYWI0\/ODY1ZGRjYzc1NmNh\/YTM2YzY1Y2I2ZGEu\/anBlZw"},"description":"2.5\", SAS 2.0 (6Gbps), 15000 об\/мин","description_list":["2.5\"","SAS 2.0 (6Gbps)","15000 об\/мин"],"micro_description":"2.5\", SAS 2.0 (6Gbps), 15000 об\/мин","micro_description_list":["2.5\"","SAS 2.0 (6Gbps)","15000 об\/мин"],"html_url":"https:\/\/catalog.onliner.by\/hdd\/hp\/qr492a","reviews":{"rating":0,"count":0,"html_url":"https:\/\/catalog.onliner.by\/hdd\/hp\/qr492a\/reviews","url":"https:\/\/catalog.api.onliner.by\/products\/qr492a\/reviews"},"review_url":null,"color_code":null,"prices":{"price_min":{"amount":"701.63","currency":"BYN","converted":{"BYN":{"amount":"701.63","currency":"BYN"}}},"price_max":{"amount":"701.63","currency":"BYN","converted":{"BYN":{"amount":"701.63","currency":"BYN"}}},"offers":{"count":1},"html_url":"https:\/\/catalog.onliner.by\/hdd\/hp\/qr492a\/prices","url":"https:\/\/shop.api.onliner.by\/products\/qr492a\/positions"},"max_installment_terms":null,"max_cobrand_cashback":null,"sale":{"is_on_sale":false,"discount":0,"min_prices_median":{"amount":"701.63","currency":"BYN"},"subscribed":false,"can_be_subscribed":true},"second":{"offers_count":0,"min_price":null,"max_price":null},"forum":{"topic_id":null,"topic_url":null,"post_url":"https:\/\/forum.onliner.by\/posting.php?mode=newtopic&f=148&device=qr492a","replies_count":null},"url":"https:\/\/catalog.api.onliner.by\/products\/qr492a","advertise":null,"stickers":null,"prime_info":{"available":false},"in_bookmarks":false,"by_parts_info":null},{"id":940104,"key":"02311ayt","parent_key":"","name":"RH2288 V3 2TB [02311AYT]","full_name":"Huawei RH2288 V3 2TB [02311AYT]","name_prefix":"Жесткий диск","extended_name":"Жесткий диск Huawei RH2288 V3 2TB [02311AYT]","status":"active","images":{"header":"https:\/\/imgproxy.onliner.by\/YVvaL2GgxoTILiYCVzK2ni1ZR-TMWMIAqtCS03Udfwc\/w:170\/h:250\/z:2\/f:jpg\/aHR0cHM6Ly9jb250\/ZW50Lm9ubGluZXIu\/YnkvY2F0YWxvZy9k\/ZXZpY2Uvb3JpZ2lu\/YWwvYzQ4NGRlM2Ez\/MWMxZDlhYmVlNDc0\/NGZiZTI0MWEwY2Mu\/anBlZw"},"description":"3.5\", SATA 3.0 (6Gbps), 7200 об\/мин, буфер 64 МБ","description_list":["3.5\"","SATA 3.0 (6Gbps)","7200 об\/мин","буфер 64 МБ"],"micro_description":"3.5\", SATA 3.0 (6Gbps), 7200 об\/мин, буфер 64 МБ","micro_description_list":["3.5\"","SATA 3.0 (6Gbps)","7200 об\/мин","буфер 64 МБ"],"html_url":"https:\/\/catalog.onliner.by\/hdd\/huawei\/02311ayt","reviews":{"rating":0,"count":0,"html_url":"https:\/\/catalog.onliner.by\/hdd\/huawei\/02311ayt\/reviews","url":"https:\/\/catalog.api.onliner.by\/products\/02311ayt\/reviews"},"review_url":null,"color_code":null,"prices":{"price_min":{"amount":"600.56","currency":"BYN","converted":{"BYN":{"amount":"600.56","currency":"BYN"}}},"price_max":{"amount":"704.75","currency":"BYN","converted":{"BYN":{"amount":"704.75","currency":"BYN"}}},"offers":{"count":21},"html_url":"https:\/\/catalog.onliner.by\/hdd\/huawei\/02311ayt\/prices","url":"https:\/\/shop.api.onliner.by\/products\/02311ayt\/positions"},"max_installment_terms":null,"max_cobrand_cashback":{"percentage":5,"label":"5% на «Клевер»"},"sale":{"is_on_sale":false,"discount":0,"min_prices_median":{"amount":"619.46","currency":"BYN"},"subscribed":false,"can_be_subscribed":true},"second":{"offers_count":0,"min_price":null,"max_price":null},"forum":{"topic_id":null,"topic_url":null,"post_url":"https:\/\/forum.onliner.by\/posting.php?mode=newtopic&f=148&device=02311ayt","replies_count":null},"url":"https:\/\/catalog.api.onliner.by\/products\/02311ayt","advertise":null,"stickers":null,"prime_info":{"available":false},"in_bookmarks":false,"by_parts_info":{"max_term":48,"monthly_payment":{"amount":"18.25","currency":"BYN"},"installment":{"periods":[3]}}},{"id":940085,"key":"02310ych","parent_key":"","name":"RH2288 V3 1TB [02310YCH]","full_name":"Huawei RH2288 V3 1TB [02310YCH]","name_prefix":"Жесткий диск","extended_name":"Жесткий диск Huawei RH2288 V3 1TB [02310YCH]","status":"active","images":{"header":"https:\/\/imgproxy.onliner.by\/YVvaL2GgxoTILiYCVzK2ni1ZR-TMWMIAqtCS03Udfwc\/w:170\/h:250\/z:2\/f:jpg\/aHR0cHM6Ly9jb250\/ZW50Lm9ubGluZXIu\/YnkvY2F0YWxvZy9k\/ZXZpY2Uvb3JpZ2lu\/YWwvYzQ4NGRlM2Ez\/MWMxZDlhYmVlNDc0\/NGZiZTI0MWEwY2Mu\/anBlZw"},"description":"2.5\", SATA 3.0 (6Gbps), 7200 об\/мин, буфер 64 МБ","description_list":["2.5\"","SATA 3.0 (6Gbps)","7200 об\/мин","буфер 64 МБ"],"micro_description":"2.5\", SATA 3.0 (6Gbps), 7200 об\/мин, буфер 64 МБ","micro_description_list":["2.5\"","SATA 3.0 (6Gbps)","7200 об\/мин","буфер 64 МБ"],"html_url":"https:\/\/catalog.onliner.by\/hdd\/huawei\/02310ych","reviews":{"rating":0,"count":0,"html_url":"https:\/\/catalog.onliner.by\/hdd\/huawei\/02310ych\/reviews","url":"https:\/\/catalog.api.onliner.by\/products\/02310ych\/reviews"},"review_url":null,"color_code":null,"prices":{"price_min":{"amount":"969.20","currency":"BYN","converted":{"BYN":{"amount":"969.20","currency":"BYN"}}},"price_max":{"amount":"969.20","currency":"BYN","converted":{"BYN":{"amount":"969.20","currency":"BYN"}}},"offers":{"count":1},"html_url":"https:\/\/catalog.onliner.by\/hdd\/huawei\/02310ych\/prices","url":"https:\/\/shop.api.onliner.by\/products\/02310ych\/positions"},"max_installment_terms":null,"max_cobrand_cashback":null,"sale":{"is_on_sale":false,"discount":0,"min_prices_median":{"amount":"1405.50","currency":"BYN"},"subscribed":false,"can_be_subscribed":true},"second":{"offers_count":0,"min_price":null,"max_price":null},"forum":{"topic_id":null,"topic_url":null,"post_url":"https:\/\/forum.onliner.by\/posting.php?mode=newtopic&f=148&device=02310ych","replies_count":null},"url":"https:\/\/catalog.api.onliner.by\/products\/02310ych","advertise":null,"stickers":null,"prime_info":{"available":false},"in_bookmarks":false,"by_parts_info":null},{"id":940083,"key":"02310ycm","parent_key":"","name":"RH2288 V3 300GB [02310YCM]","full_name":"Huawei RH2288 V3 300GB [02310YCM]","name_prefix":"Жесткий диск","extended_name":"Жесткий диск Huawei RH2288 V3 300GB [02310YCM]","status":"active","images":{"header":"https:\/\/imgproxy.onliner.by\/YVvaL2GgxoTILiYCVzK2ni1ZR-TMWMIAqtCS03Udfwc\/w:170\/h:250\/z:2\/f:jpg\/aHR0cHM6Ly9jb250\/ZW50Lm9ubGluZXIu\/YnkvY2F0YWxvZy9k\/ZXZpY2Uvb3JpZ2lu\/YWwvYzQ4NGRlM2Ez\/MWMxZDlhYmVlNDc0\/NGZiZTI0MWEwY2Mu\/anBlZw"},"description":"2.5\", SAS 1.0 (3Gbps), 10000 об\/мин, буфер 16 МБ","description_list":["2.5\"","SAS 1.0 (3Gbps)","10000 об\/мин","буфер 16 МБ"],"micro_description":"2.5\", SAS 1.0 (3Gbps), 10000 об\/мин, буфер 16 МБ","micro_description_list":["2.5\"","SAS 1.0 (3Gbps)","10000 об\/мин","буфер 16 МБ"],"html_url":"https:\/\/catalog.onliner.by\/hdd\/huawei\/02310ycm","reviews":{"rating":0,"count":0,"html_url":"https:\/\/catalog.onliner.by\/hdd\/huawei\/02310ycm\/reviews","url":"https:\/\/catalog.api.onliner.by\/products\/02310ycm\/reviews"},"review_url":null,"color_code":null,"prices":{"price_min":{"amount":"1494.62","currency":"BYN","converted":{"BYN":{"amount":"1494.62","currency":"BYN"}}},"price_max":{"amount":"1494.62","currency":"BYN","converted":{"BYN":{"amount":"1494.62","currency":"BYN"}}},"offers":{"count":1},"html_url":"https:\/\/catalog.onliner.by\/hdd\/huawei\/02310ycm\/prices","url":"https:\/\/shop.api.onliner.by\/products\/02310ycm\/positions"},"max_installment_terms":null,"max_cobrand_cashback":null,"sale":{"is_on_sale":false,"discount":0,"min_prices_median":{"amount":"1494.62","currency":"BYN"},"subscribed":false,"can_be_subscribed":true},"second":{"offers_count":0,"min_price":null,"max_price":null},"forum":{"topic_id":null,"topic_url":null,"post_url":"https:\/\/forum.onliner.by\/posting.php?mode=newtopic&f=148&device=02310ycm","replies_count":null},"url":"https:\/\/catalog.api.onliner.by\/products\/02310ycm","advertise":null,"stickers":null,"prime_info":{"available":false},"in_bookmarks":false,"by_parts_info":null},{"id":939754,"key":"wd2002ffsx","parent_key":"","name":"Red Pro 2TB [WD2002FFSX]","full_name":"WD Red Pro 2TB [WD2002FFSX]","name_prefix":"Жесткий диск","extended_name":"Жесткий диск WD Red Pro 2TB [WD2002FFSX]","status":"active","images":{"header":"https:\/\/imgproxy.onliner.by\/dv7cIo0kksOi-8UXdfAmn9wlmIxgrOFUII6LssyvH0o\/w:170\/h:250\/z:2\/f:jpg\/aHR0cHM6Ly9jb250\/ZW50Lm9ubGluZXIu\/YnkvY2F0YWxvZy9k\/ZXZpY2Uvb3JpZ2lu\/YWwvODZkMzM2MzA3\/NTY5ODJjYTNjYzRm\/ZTcyYmJiODJmMjYu\/anBlZw"},"description":"3.5\", SATA 3.0 (6Gbps), 7200 об\/мин, буфер 64 МБ","description_list":["3.5\"","SATA 3.0 (6Gbps)","7200 об\/мин","буфер 64 МБ"],"micro_description":"3.5\", SATA 3.0 (6Gbps), 7200 об\/мин, буфер 64 МБ","micro_description_list":["3.5\"","SATA 3.0 (6Gbps)","7200 об\/мин","буфер 64 МБ"],"html_url":"https:\/\/catalog.onliner.by\/hdd\/westerndigital\/wd2002ffsx","reviews":{"rating":23,"count":3,"html_url":"https:\/\/catalog.onliner.by\/hdd\/westerndigital\/wd2002ffsx\/reviews","url":"https:\/\/catalog.api.onliner.by\/products\/wd2002ffsx\/reviews"},"review_url":null,"color_code":null,"prices":{"price_min":{"amount":"573.94","currency":"BYN","converted":{"BYN":{"amount":"573.94","currency":"BYN"}}},"price_max":{"amount":"646.49","currency":"BYN","converted":{"BYN":{"amount":"646.49","currency":"BYN"}}},"offers":{"count":38},"html_url":"https:\/\/catalog.onliner.by\/hdd\/westerndigital\/wd2002ffsx\/prices","url":"https:\/\/shop.api.onliner.by\/products\/wd2002ffsx\/positions"},"max_installment_terms":{"all":{"term":4,"label":"Рассрочка до 4 месяцев"}},"max_cobrand_cashback":{"percentage":5,"label":"5% на «Клевер»"},"sale":{"is_on_sale":false,"discount":0,"min_prices_median":{"amount":"574.01","currency":"BYN"},"subscribed":false,"can_be_subscribed":true},"second":{"offers_count":0,"min_price":null,"max_price":null},"forum":{"topic_id":23928370,"topic_url":"https:\/\/forum.onliner.by\/viewtopic.php?t=23928370","post_url":"https:\/\/forum.onliner.by\/posting.php?mode=newtopic&f=148&device=wd2002ffsx","replies_count":2},"url":"https:\/\/catalog.api.onliner.by\/products\/wd2002ffsx","advertise":null,"stickers":null,"prime_info":{"available":false},"in_bookmarks":false,"by_parts_info":{"max_term":48,"monthly_payment":{"amount":"17.44","currency":"BYN"},"installment":{"periods":[3]}}},{"id":871042,"key":"j9f48a","parent_key":"","name":"1.2TB [J9F48A]","full_name":"HP 1.2TB [J9F48A]","name_prefix":"Жесткий диск","extended_name":"Жесткий диск HP 1.2TB [J9F48A]","status":"active","images":{"header":"https:\/\/imgproxy.onliner.by\/o99y86b87Apw-KhdpaBjLVDiKHYhKtq22V8HGw2Nfbw\/w:170\/h:250\/z:2\/f:jpg\/aHR0cHM6Ly9jb250\/ZW50Lm9ubGluZXIu\/YnkvY2F0YWxvZy9k\/ZXZpY2Uvb3JpZ2lu\/YWwvNDAyOWRjYzBl\/NzMwNjFkOGQ3OGFl\/NDBmOGRmM2RiMTMu\/cG5n"},"description":"2.5\", SAS 3.0 (12Gbps), 10000 об\/мин","description_list":["2.5\"","SAS 3.0 (12Gbps)","10000 об\/мин"],"micro_description":"2.5\", SAS 3.0 (12Gbps), 10000 об\/мин","micro_description_list":["2.5\"","SAS 3.0 (12Gbps)","10000 об\/мин"],"html_url":"https:\/\/catalog.onliner.by\/hdd\/hp\/j9f48a","reviews":{"rating":0,"count":0,"html_url":"https:\/\/catalog.onliner.by\/hdd\/hp\/j9f48a\/reviews","url":"https:\/\/catalog.api.onliner.by\/products\/j9f48a\/reviews"},"review_url":null,"color_code":null,"prices":{"price_min":{"amount":"1015.52","currency":"BYN","converted":{"BYN":{"amount":"1015.52","currency":"BYN"}}},"price_max":{"amount":"1597.32","currency":"BYN","converted":{"BYN":{"amount":"1597.32","currency":"BYN"}}},"offers":{"count":12},"html_url":"https:\/\/catalog.onliner.by\/hdd\/hp\/j9f48a\/prices","url":"https:\/\/shop.api.onliner.by\/products\/j9f48a\/positions"},"max_installment_terms":null,"max_cobrand_cashback":{"percentage":5,"label":"5% на «Клевер»"},"sale":{"is_on_sale":false,"discount":0,"min_prices_median":{"amount":"1015.52","currency":"BYN"},"subscribed":false,"can_be_subscribed":true},"second":{"offers_count":0,"min_price":null,"max_price":null},"forum":{"topic_id":null,"topic_url":null,"post_url":"https:\/\/forum.onliner.by\/posting.php?mode=newtopic&f=148&device=j9f48a","replies_count":null},"url":"https:\/\/catalog.api.onliner.by\/products\/j9f48a","advertise":null,"stickers":null,"prime_info":{"available":false},"in_bookmarks":false,"by_parts_info":{"max_term":48,"monthly_payment":{"amount":"30.85","currency":"BYN"},"installment":{"periods":[3]}}},{"id":871017,"key":"ap861a","parent_key":"","name":"1TB [AP861A]","full_name":"HP 1TB [AP861A]","name_prefix":"Жесткий диск","extended_name":"Жесткий диск HP 1TB [AP861A]","status":"active","images":{"header":"https:\/\/imgproxy.onliner.by\/o99y86b87Apw-KhdpaBjLVDiKHYhKtq22V8HGw2Nfbw\/w:170\/h:250\/z:2\/f:jpg\/aHR0cHM6Ly9jb250\/ZW50Lm9ubGluZXIu\/YnkvY2F0YWxvZy9k\/ZXZpY2Uvb3JpZ2lu\/YWwvNDAyOWRjYzBl\/NzMwNjFkOGQ3OGFl\/NDBmOGRmM2RiMTMu\/cG5n"},"description":"3.5\", SAS 2.0 (6Gbps), 7200 об\/мин","description_list":["3.5\"","SAS 2.0 (6Gbps)","7200 об\/мин"],"micro_description":"3.5\", SAS 2.0 (6Gbps), 7200 об\/мин","micro_description_list":["3.5\"","SAS 2.0 (6Gbps)","7200 об\/мин"],"html_url":"https:\/\/catalog.onliner.by\/hdd\/hp\/ap861a","reviews":{"rating":0,"count":0,"html_url":"https:\/\/catalog.onliner.by\/hdd\/hp\/ap861a\/reviews","url":"https:\/\/catalog.api.onliner.by\/products\/ap861a\/reviews"},"review_url":null,"color_code":null,"prices":{"price_min":{"amount":"663.50","currency":"BYN","converted":{"BYN":{"amount":"663.50","currency":"BYN"}}},"price_max":{"amount":"663.50","currency":"BYN","converted":{"BYN":{"amount":"663.50","currency":"BYN"}}},"offers":{"count":1},"html_url":"https:\/\/catalog.onliner.by\/hdd\/hp\/ap861a\/prices","url":"https:\/\/shop.api.onliner.by\/products\/ap861a\/positions"},"max_installment_terms":null,"max_cobrand_cashback":null,"sale":{"is_on_sale":false,"discount":0,"min_prices_median":{"amount":"663.50","currency":"BYN"},"subscribed":false,"can_be_subscribed":true},"second":{"offers_count":0,"min_price":null,"max_price":null},"forum":{"topic_id":null,"topic_url":null,"post_url":"https:\/\/forum.onliner.by\/posting.php?mode=newtopic&f=148&device=ap861a","replies_count":null},"url":"https:\/\/catalog.api.onliner.by\/products\/ap861a","advertise":null,"stickers":null,"prime_info":{"available":false},"in_bookmarks":false,"by_parts_info":null},{"id":871015,"key":"655708b21","parent_key":"","name":"655708-B21 500GB","full_name":"HP 655708-B21 500GB","name_prefix":"Жесткий диск","extended_name":"Жесткий диск HP 655708-B21 500GB","status":"active","images":{"header":"https:\/\/imgproxy.onliner.by\/o99y86b87Apw-KhdpaBjLVDiKHYhKtq22V8HGw2Nfbw\/w:170\/h:250\/z:2\/f:jpg\/aHR0cHM6Ly9jb250\/ZW50Lm9ubGluZXIu\/YnkvY2F0YWxvZy9k\/ZXZpY2Uvb3JpZ2lu\/YWwvNDAyOWRjYzBl\/NzMwNjFkOGQ3OGFl\/NDBmOGRmM2RiMTMu\/cG5n"},"description":"2.5\", SATA 3.0 (6Gbps), 7200 об\/мин","description_list":["2.5\"","SATA 3.0 (6Gbps)","7200 об\/мин"],"micro_description":"2.5\", SATA 3.0 (6Gbps), 7200 об\/мин","micro_description_list":["2.5\"","SATA 3.0 (6Gbps)","7200 об\/мин"],"html_url":"https:\/\/catalog.onliner.by\/hdd\/hp\/655708b21","reviews":{"rating":0,"count":0,"html_url":"https:\/\/catalog.onliner.by\/hdd\/hp\/655708b21\/reviews","url":"https:\/\/catalog.api.onliner.by\/products\/655708b21\/reviews"},"review_url":null,"color_code":null,"prices":{"price_min":{"amount":"497.16","currency":"BYN","converted":{"BYN":{"amount":"497.16","currency":"BYN"}}},"price_max":{"amount":"1671.28","currency":"BYN","converted":{"BYN":{"amount":"1671.28","currency":"BYN"}}},"offers":{"count":3},"html_url":"https:\/\/catalog.onliner.by\/hdd\/hp\/655708b21\/prices","url":"https:\/\/shop.api.onliner.by\/products\/655708b21\/positions"},"max_installment_terms":null,"max_cobrand_cashback":null,"sale":{"is_on_sale":false,"discount":0,"min_prices_median":{"amount":"497.16","currency":"BYN"},"subscribed":false,"can_be_subscribed":true},"second":{"offers_count":0,"min_price":null,"max_price":null},"forum":{"topic_id":null,"topic_url":null,"post_url":"https:\/\/forum.onliner.by\/posting.php?mode=newtopic&f=148&device=655708b21","replies_count":null},"url":"https:\/\/catalog.api.onliner.by\/products\/655708b21","advertise":null,"stickers":null,"prime_info":{"available":false},"in_bookmarks":false,"by_parts_info":null},{"id":871006,"key":"765424b21","parent_key":"","name":"600GB [765424-B21]","full_name":"HP 600GB [765424-B21]","name_prefix":"Жесткий диск","extended_name":"Жесткий диск HP 600GB [765424-B21]","status":"active","images":{"header":"https:\/\/imgproxy.onliner.by\/o99y86b87Apw-KhdpaBjLVDiKHYhKtq22V8HGw2Nfbw\/w:170\/h:250\/z:2\/f:jpg\/aHR0cHM6Ly9jb250\/ZW50Lm9ubGluZXIu\/YnkvY2F0YWxvZy9k\/ZXZpY2Uvb3JpZ2lu\/YWwvNDAyOWRjYzBl\/NzMwNjFkOGQ3OGFl\/NDBmOGRmM2RiMTMu\/cG5n"},"description":"3.5\", SAS 3.0 (12Gbps), 15000 об\/мин, время доступа 2.9 мс","description_list":["3.5\"","SAS 3.0 (12Gbps)","15000 об\/мин","время доступа 2.9 мс"],"micro_description":"3.5\", SAS 3.0 (12Gbps), 15000 об\/мин","micro_description_list":["3.5\"","SAS 3.0 (12Gbps)","15000 об\/мин"],"html_url":"https:\/\/catalog.onliner.by\/hdd\/hp\/765424b21","reviews":{"rating":0,"count":0,"html_url":"https:\/\/catalog.onliner.by\/hdd\/hp\/765424b21\/reviews","url":"https:\/\/catalog.api.onliner.by\/products\/765424b21\/reviews"},"review_url":null,"color_code":null,"prices":{"price_min":{"amount":"1242.97","currency":"BYN","converted":{"BYN":{"amount":"1242.97","currency":"BYN"}}},"price_max":{"amount":"1242.97","currency":"BYN","converted":{"BYN":{"amount":"1242.97","currency":"BYN"}}},"offers":{"count":1},"html_url":"https:\/\/catalog.onliner.by\/hdd\/hp\/765424b21\/prices","url":"https:\/\/shop.api.onliner.by\/products\/765424b21\/positions"},"max_installment_terms":null,"max_cobrand_cashback":null,"sale":{"is_on_sale":false,"discount":0,"min_prices_median":{"amount":"1216.23","currency":"BYN"},"subscribed":false,"can_be_subscribed":true},"second":{"offers_count":0,"min_price":null,"max_price":null},"forum":{"topic_id":null,"topic_url":null,"post_url":"https:\/\/forum.onliner.by\/posting.php?mode=newtopic&f=148&device=765424b21","replies_count":null},"url":"https:\/\/catalog.api.onliner.by\/products\/765424b21","advertise":null,"stickers":null,"prime_info":{"available":false},"in_bookmarks":false,"by_parts_info":null},{"id":871005,"key":"753874b21","parent_key":"","name":"6TB [753874-B21]","full_name":"HP 6TB [753874-B21]","name_prefix":"Жесткий диск","extended_name":"Жесткий диск HP 6TB [753874-B21]","status":"active","images":{"header":"https:\/\/imgproxy.onliner.by\/o99y86b87Apw-KhdpaBjLVDiKHYhKtq22V8HGw2Nfbw\/w:170\/h:250\/z:2\/f:jpg\/aHR0cHM6Ly9jb250\/ZW50Lm9ubGluZXIu\/YnkvY2F0YWxvZy9k\/ZXZpY2Uvb3JpZ2lu\/YWwvNDAyOWRjYzBl\/NzMwNjFkOGQ3OGFl\/NDBmOGRmM2RiMTMu\/cG5n"},"description":"3.5\", SAS 2.0 (6Gbps), 7200 об\/мин","description_list":["3.5\"","SAS 2.0 (6Gbps)","7200 об\/мин"],"micro_description":"3.5\", SAS 2.0 (6Gbps), 7200 об\/мин","micro_description_list":["3.5\"","SAS 2.0 (6Gbps)","7200 об\/мин"],"html_url":"https:\/\/catalog.onliner.by\/hdd\/hp\/753874b21","reviews":{"rating":0,"count":0,"html_url":"https:\/\/catalog.onliner.by\/hdd\/hp\/753874b21\/reviews","url":"https:\/\/catalog.api.onliner.by\/products\/753874b21\/reviews"},"review_url":null,"color_code":null,"prices":{"price_min":{"amount":"2080.84","currency":"BYN","converted":{"BYN":{"amount":"2080.84","currency":"BYN"}}},"price_max":{"amount":"2080.84","currency":"BYN","converted":{"BYN":{"amount":"2080.84","currency":"BYN"}}},"offers":{"count":1},"html_url":"https:\/\/catalog.onliner.by\/hdd\/hp\/753874b21\/prices","url":"https:\/\/shop.api.onliner.by\/products\/753874b21\/positions"},"max_installment_terms":null,"max_cobrand_cashback":null,"sale":{"is_on_sale":false,"discount":0,"min_prices_median":{"amount":"1980.84","currency":"BYN"},"subscribed":false,"can_be_subscribed":true},"second":{"offers_count":0,"min_price":null,"max_price":null},"forum":{"topic_id":null,"topic_url":null,"post_url":"https:\/\/forum.onliner.by\/posting.php?mode=newtopic&f=148&device=753874b21","replies_count":null},"url":"https:\/\/catalog.api.onliner.by\/products\/753874b21","advertise":null,"stickers":null,"prime_info":{"available":false},"in_bookmarks":false,"by_parts_info":null},{"id":867428,"key":"737394b21","parent_key":"","name":"450GB [737394-B21]","full_name":"HP 450GB [737394-B21]","name_prefix":"Жесткий диск","extended_name":"Жесткий диск HP 450GB [737394-B21]","status":"active","images":{"header":"https:\/\/imgproxy.onliner.by\/vBlLl-nXdpwSYKyToa0COXhdgeWapErG6Ey1u9Fnip8\/w:170\/h:250\/z:2\/f:jpg\/aHR0cHM6Ly9jb250\/ZW50Lm9ubGluZXIu\/YnkvY2F0YWxvZy9k\/ZXZpY2Uvb3JpZ2lu\/YWwvMzkwZDNhOGQ1\/MGZmYmUxNDIyYWVm\/YTQ3YjRlNTRjMWIu\/anBn"},"description":"3.5\", SAS 3.0 (12Gbps), 15000 об\/мин, время доступа 2.9 мс","description_list":["3.5\"","SAS 3.0 (12Gbps)","15000 об\/мин","время доступа 2.9 мс"],"micro_description":"3.5\", SAS 3.0 (12Gbps), 15000 об\/мин","micro_description_list":["3.5\"","SAS 3.0 (12Gbps)","15000 об\/мин"],"html_url":"https:\/\/catalog.onliner.by\/hdd\/hp\/737394b21","reviews":{"rating":0,"count":0,"html_url":"https:\/\/catalog.onliner.by\/hdd\/hp\/737394b21\/reviews","url":"https:\/\/catalog.api.onliner.by\/products\/737394b21\/reviews"},"review_url":null,"color_code":null,"prices":{"price_min":{"amount":"424.00","currency":"BYN","converted":{"BYN":{"amount":"424.00","currency":"BYN"}}},"price_max":{"amount":"1513.74","currency":"BYN","converted":{"BYN":{"amount":"1513.74","currency":"BYN"}}},"offers":{"count":14},"html_url":"https:\/\/catalog.onliner.by\/hdd\/hp\/737394b21\/prices","url":"https:\/\/shop.api.onliner.by\/products\/737394b21\/positions"},"max_installment_terms":null,"max_cobrand_cashback":{"percentage":5,"label":"5% на «Клевер»"},"sale":{"is_on_sale":true,"discount":10,"min_prices_median":{"amount":"473.68","currency":"BYN"},"subscribed":false,"can_be_subscribed":true},"second":{"offers_count":0,"min_price":null,"max_price":null},"forum":{"topic_id":null,"topic_url":null,"post_url":"https:\/\/forum.onliner.by\/posting.php?mode=newtopic&f=148&device=737394b21","replies_count":null},"url":"https:\/\/catalog.api.onliner.by\/products\/737394b21","advertise":null,"stickers":null,"prime_info":{"available":false},"in_bookmarks":false,"by_parts_info":{"max_term":48,"monthly_payment":{"amount":"12.88","currency":"BYN"},"installment":{"periods":[3]}}},{"id":867427,"key":"759210b21","parent_key":"","name":"450GB [759210-B21]","full_name":"HP 450GB [759210-B21]","name_prefix":"Жесткий диск","extended_name":"Жесткий диск HP 450GB [759210-B21]","status":"active","images":{"header":"https:\/\/imgproxy.onliner.by\/vBlLl-nXdpwSYKyToa0COXhdgeWapErG6Ey1u9Fnip8\/w:170\/h:250\/z:2\/f:jpg\/aHR0cHM6Ly9jb250\/ZW50Lm9ubGluZXIu\/YnkvY2F0YWxvZy9k\/ZXZpY2Uvb3JpZ2lu\/YWwvMzkwZDNhOGQ1\/MGZmYmUxNDIyYWVm\/YTQ3YjRlNTRjMWIu\/anBn"},"description":"2.5\", SAS 3.0 (12Gbps), 15000 об\/мин, время доступа 2.9 мс","description_list":["2.5\"","SAS 3.0 (12Gbps)","15000 об\/мин","время доступа 2.9 мс"],"micro_description":"2.5\", SAS 3.0 (12Gbps), 15000 об\/мин","micro_description_list":["2.5\"","SAS 3.0 (12Gbps)","15000 об\/мин"],"html_url":"https:\/\/catalog.onliner.by\/hdd\/hp\/759210b21","reviews":{"rating":0,"count":0,"html_url":"https:\/\/catalog.onliner.by\/hdd\/hp\/759210b21\/reviews","url":"https:\/\/catalog.api.onliner.by\/products\/759210b21\/reviews"},"review_url":null,"color_code":null,"prices":{"price_min":{"amount":"698.33","currency":"BYN","converted":{"BYN":{"amount":"698.33","currency":"BYN"}}},"price_max":{"amount":"1565.66","currency":"BYN","converted":{"BYN":{"amount":"1565.66","currency":"BYN"}}},"offers":{"count":4},"html_url":"https:\/\/catalog.onliner.by\/hdd\/hp\/759210b21\/prices","url":"https:\/\/shop.api.onliner.by\/products\/759210b21\/positions"},"max_installment_terms":null,"max_cobrand_cashback":null,"sale":{"is_on_sale":false,"discount":0,"min_prices_median":{"amount":"698.33","currency":"BYN"},"subscribed":false,"can_be_subscribed":true},"second":{"offers_count":0,"min_price":null,"max_price":null},"forum":{"topic_id":null,"topic_url":null,"post_url":"https:\/\/forum.onliner.by\/posting.php?mode=newtopic&f=148&device=759210b21","replies_count":null},"url":"https:\/\/catalog.api.onliner.by\/products\/759210b21","advertise":null,"stickers":null,"prime_info":{"available":false},"in_bookmarks":false,"by_parts_info":null},{"id":867424,"key":"m0s90a","parent_key":"","name":"8TB [M0S90A]","full_name":"HP 8TB [M0S90A]","name_prefix":"Жесткий диск","extended_name":"Жесткий диск HP 8TB [M0S90A]","status":"active","images":{"header":"https:\/\/imgproxy.onliner.by\/vBlLl-nXdpwSYKyToa0COXhdgeWapErG6Ey1u9Fnip8\/w:170\/h:250\/z:2\/f:jpg\/aHR0cHM6Ly9jb250\/ZW50Lm9ubGluZXIu\/YnkvY2F0YWxvZy9k\/ZXZpY2Uvb3JpZ2lu\/YWwvMzkwZDNhOGQ1\/MGZmYmUxNDIyYWVm\/YTQ3YjRlNTRjMWIu\/anBn"},"description":"3.5\", SAS 3.0 (12Gbps), 7200 об\/мин","description_list":["3.5\"","SAS 3.0 (12Gbps)","7200 об\/мин"],"micro_description":"3.5\", SAS 3.0 (12Gbps), 7200 об\/мин","micro_description_list":["3.5\"","SAS 3.0 (12Gbps)","7200 об\/мин"],"html_url":"https:\/\/catalog.onliner.by\/hdd\/hp\/m0s90a","reviews":{"rating":0,"count":0,"html_url":"https:\/\/catalog.onliner.by\/hdd\/hp\/m0s90a\/reviews","url":"https:\/\/catalog.api.onliner.by\/products\/m0s90a\/reviews"},"review_url":null,"color_code":null,"prices":{"price_min":{"amount":"1701.00","currency":"BYN","converted":{"BYN":{"amount":"1701.00","currency":"BYN"}}},"price_max":{"amount":"1701.00","currency":"BYN","converted":{"BYN":{"amount":"1701.00","currency":"BYN"}}},"offers":{"count":1},"html_url":"https:\/\/catalog.onliner.by\/hdd\/hp\/m0s90a\/prices","url":"https:\/\/shop.api.onliner.by\/products\/m0s90a\/positions"},"max_installment_terms":null,"max_cobrand_cashback":null,"sale":{"is_on_sale":false,"discount":0,"min_prices_median":{"amount":"1701.00","currency":"BYN"},"subscribed":false,"can_be_subscribed":true},"second":{"offers_count":0,"min_price":null,"max_price":null},"forum":{"topic_id":null,"topic_url":null,"post_url":"https:\/\/forum.onliner.by\/posting.php?mode=newtopic&f=148&device=m0s90a","replies_count":null},"url":"https:\/\/catalog.api.onliner.by\/products\/m0s90a","advertise":null,"stickers":null,"prime_info":{"available":false},"in_bookmarks":false,"by_parts_info":null},{"id":867423,"key":"k2q82a","parent_key":"","name":"4TB [K2Q82A]","full_name":"HP 4TB [K2Q82A]","name_prefix":"Жесткий диск","extended_name":"Жесткий диск HP 4TB [K2Q82A]","status":"active","images":{"header":"https:\/\/imgproxy.onliner.by\/vBlLl-nXdpwSYKyToa0COXhdgeWapErG6Ey1u9Fnip8\/w:170\/h:250\/z:2\/f:jpg\/aHR0cHM6Ly9jb250\/ZW50Lm9ubGluZXIu\/YnkvY2F0YWxvZy9k\/ZXZpY2Uvb3JpZ2lu\/YWwvMzkwZDNhOGQ1\/MGZmYmUxNDIyYWVm\/YTQ3YjRlNTRjMWIu\/anBn"},"description":"3.5\", SAS 3.0 (12Gbps), 7200 об\/мин","description_list":["3.5\"","SAS 3.0 (12Gbps)","7200 об\/мин"],"micro_description":"3.5\", SAS 3.0 (12Gbps), 7200 об\/мин","micro_description_list":["3.5\"","SAS 3.0 (12Gbps)","7200 об\/мин"],"html_url":"https:\/\/catalog.onliner.by\/hdd\/hp\/k2q82a","reviews":{"rating":0,"count":0,"html_url":"https:\/\/catalog.onliner.by\/hdd\/hp\/k2q82a\/reviews","url":"https:\/\/catalog.api.onliner.by\/products\/k2q82a\/reviews"},"review_url":null,"color_code":null,"prices":{"price_min":{"amount":"1183.93","currency":"BYN","converted":{"BYN":{"amount":"1183.93","currency":"BYN"}}},"price_max":{"amount":"1183.93","currency":"BYN","converted":{"BYN":{"amount":"1183.93","currency":"BYN"}}},"offers":{"count":1},"html_url":"https:\/\/catalog.onliner.by\/hdd\/hp\/k2q82a\/prices","url":"https:\/\/shop.api.onliner.by\/products\/k2q82a\/positions"},"max_installment_terms":null,"max_cobrand_cashback":null,"sale":{"is_on_sale":false,"discount":0,"min_prices_median":{"amount":"1183.93","currency":"BYN"},"subscribed":false,"can_be_subscribed":true},"second":{"offers_count":0,"min_price":null,"max_price":null},"forum":{"topic_id":null,"topic_url":null,"post_url":"https:\/\/forum.onliner.by\/posting.php?mode=newtopic&f=148&device=k2q82a","replies_count":null},"url":"https:\/\/catalog.api.onliner.by\/products\/k2q82a","advertise":null,"stickers":null,"prime_info":{"available":false},"in_bookmarks":false,"by_parts_info":null},{"id":867422,"key":"j9f51a","parent_key":"","name":"2TB [J9F51A]","full_name":"HP 2TB [J9F51A]","name_prefix":"Жесткий диск","extended_name":"Жесткий диск HP 2TB [J9F51A]","status":"active","images":{"header":"https:\/\/imgproxy.onliner.by\/vBlLl-nXdpwSYKyToa0COXhdgeWapErG6Ey1u9Fnip8\/w:170\/h:250\/z:2\/f:jpg\/aHR0cHM6Ly9jb250\/ZW50Lm9ubGluZXIu\/YnkvY2F0YWxvZy9k\/ZXZpY2Uvb3JpZ2lu\/YWwvMzkwZDNhOGQ1\/MGZmYmUxNDIyYWVm\/YTQ3YjRlNTRjMWIu\/anBn"},"description":"2.5\", SAS 3.0 (12Gbps), 7200 об\/мин","description_list":["2.5\"","SAS 3.0 (12Gbps)","7200 об\/мин"],"micro_description":"2.5\", SAS 3.0 (12Gbps), 7200 об\/мин","micro_description_list":["2.5\"","SAS 3.0 (12Gbps)","7200 об\/мин"],"html_url":"https:\/\/catalog.onliner.by\/hdd\/hp\/j9f51a","reviews":{"rating":0,"count":0,"html_url":"https:\/\/catalog.onliner.by\/hdd\/hp\/j9f51a\/reviews","url":"https:\/\/catalog.api.onliner.by\/products\/j9f51a\/reviews"},"review_url":null,"color_code":null,"prices":{"price_min":{"amount":"1260.51","currency":"BYN","converted":{"BYN":{"amount":"1260.51","currency":"BYN"}}},"price_max":{"amount":"1260.51","currency":"BYN","converted":{"BYN":{"amount":"1260.51","currency":"BYN"}}},"offers":{"count":9},"html_url":"https:\/\/catalog.onliner.by\/hdd\/hp\/j9f51a\/prices","url":"https:\/\/shop.api.onliner.by\/products\/j9f51a\/positions"},"max_installment_terms":{"all":{"term":4,"label":"Рассрочка до 4 месяцев"}},"max_cobrand_cashback":{"percentage":5,"label":"5% на «Клевер»"},"sale":{"is_on_sale":false,"discount":0,"min_prices_median":{"amount":"1260.51","currency":"BYN"},"subscribed":false,"can_be_subscribed":true},"second":{"offers_count":0,"min_price":null,"max_price":null},"forum":{"topic_id":null,"topic_url":null,"post_url":"https:\/\/forum.onliner.by\/posting.php?mode=newtopic&f=148&device=j9f51a","replies_count":null},"url":"https:\/\/catalog.api.onliner.by\/products\/j9f51a","advertise":null,"stickers":null,"prime_info":{"available":false},"in_bookmarks":false,"by_parts_info":{"max_term":48,"monthly_payment":{"amount":"38.30","currency":"BYN"},"installment":{"periods":[3]}}},{"id":867421,"key":"j9f44a","parent_key":"","name":"300GB [J9F44A]","full_name":"HP 300GB [J9F44A]","name_prefix":"Жесткий диск","extended_name":"Жесткий диск HP 300GB [J9F44A]","status":"active","images":{"header":"https:\/\/imgproxy.onliner.by\/vBlLl-nXdpwSYKyToa0COXhdgeWapErG6Ey1u9Fnip8\/w:170\/h:250\/z:2\/f:jpg\/aHR0cHM6Ly9jb250\/ZW50Lm9ubGluZXIu\/YnkvY2F0YWxvZy9k\/ZXZpY2Uvb3JpZ2lu\/YWwvMzkwZDNhOGQ1\/MGZmYmUxNDIyYWVm\/YTQ3YjRlNTRjMWIu\/anBn"},"description":"2.5\", SAS 3.0 (12Gbps), 10000 об\/мин","description_list":["2.5\"","SAS 3.0 (12Gbps)","10000 об\/мин"],"micro_description":"2.5\", SAS 3.0 (12Gbps), 10000 об\/мин","micro_description_list":["2.5\"","SAS 3.0 (12Gbps)","10000 об\/мин"],"html_url":"https:\/\/catalog.onliner.by\/hdd\/hp\/j9f44a","reviews":{"rating":0,"count":0,"html_url":"https:\/\/catalog.onliner.by\/hdd\/hp\/j9f44a\/reviews","url":"https:\/\/catalog.api.onliner.by\/products\/j9f44a\/reviews"},"review_url":null,"color_code":null,"prices":{"price_min":{"amount":"606.00","currency":"BYN","converted":{"BYN":{"amount":"606.00","currency":"BYN"}}},"price_max":{"amount":"982.69","currency":"BYN","converted":{"BYN":{"amount":"982.69","currency":"BYN"}}},"offers":{"count":3},"html_url":"https:\/\/catalog.onliner.by\/hdd\/hp\/j9f44a\/prices","url":"https:\/\/shop.api.onliner.by\/products\/j9f44a\/positions"},"max_installment_terms":null,"max_cobrand_cashback":null,"sale":{"is_on_sale":false,"discount":0,"min_prices_median":{"amount":"606.00","currency":"BYN"},"subscribed":false,"can_be_subscribed":true},"second":{"offers_count":0,"min_price":null,"max_price":null},"forum":{"topic_id":null,"topic_url":null,"post_url":"https:\/\/forum.onliner.by\/posting.php?mode=newtopic&f=148&device=j9f44a","replies_count":null},"url":"https:\/\/catalog.api.onliner.by\/products\/j9f44a","advertise":null,"stickers":null,"prime_info":{"available":false},"in_bookmarks":false,"by_parts_info":null},{"id":867417,"key":"j9f50a","parent_key":"","name":"1TB [J9F50A]","full_name":"HP 1TB [J9F50A]","name_prefix":"Жесткий диск","extended_name":"Жесткий диск HP 1TB [J9F50A]","status":"active","images":{"header":"https:\/\/imgproxy.onliner.by\/vBlLl-nXdpwSYKyToa0COXhdgeWapErG6Ey1u9Fnip8\/w:170\/h:250\/z:2\/f:jpg\/aHR0cHM6Ly9jb250\/ZW50Lm9ubGluZXIu\/YnkvY2F0YWxvZy9k\/ZXZpY2Uvb3JpZ2lu\/YWwvMzkwZDNhOGQ1\/MGZmYmUxNDIyYWVm\/YTQ3YjRlNTRjMWIu\/anBn"},"description":"2.5\", SAS 3.0 (12Gbps), 7200 об\/мин","description_list":["2.5\"","SAS 3.0 (12Gbps)","7200 об\/мин"],"micro_description":"2.5\", SAS 3.0 (12Gbps), 7200 об\/мин","micro_description_list":["2.5\"","SAS 3.0 (12Gbps)","7200 об\/мин"],"html_url":"https:\/\/catalog.onliner.by\/hdd\/hp\/j9f50a","reviews":{"rating":0,"count":0,"html_url":"https:\/\/catalog.onliner.by\/hdd\/hp\/j9f50a\/reviews","url":"https:\/\/catalog.api.onliner.by\/products\/j9f50a\/reviews"},"review_url":null,"color_code":null,"prices":{"price_min":{"amount":"722.24","currency":"BYN","converted":{"BYN":{"amount":"722.24","currency":"BYN"}}},"price_max":{"amount":"1551.28","currency":"BYN","converted":{"BYN":{"amount":"1551.28","currency":"BYN"}}},"offers":{"count":5},"html_url":"https:\/\/catalog.onliner.by\/hdd\/hp\/j9f50a\/prices","url":"https:\/\/shop.api.onliner.by\/products\/j9f50a\/positions"},"max_installment_terms":null,"max_cobrand_cashback":{"percentage":5,"label":"5% на «Клевер»"},"sale":{"is_on_sale":false,"discount":0,"min_prices_median":{"amount":"722.24","currency":"BYN"},"subscribed":false,"can_be_subscribed":true},"second":{"offers_count":0,"min_price":null,"max_price":null},"forum":{"topic_id":null,"topic_url":null,"post_url":"https:\/\/forum.onliner.by\/posting.php?mode=newtopic&f=148&device=j9f50a","replies_count":null},"url":"https:\/\/catalog.api.onliner.by\/products\/j9f50a","advertise":null,"stickers":null,"prime_info":{"available":false},"in_bookmarks":false,"by_parts_info":{"max_term":48,"monthly_payment":{"amount":"47.13","currency":"BYN"},"installment":{"periods":[3]}}},{"id":867416,"key":"781518b21","parent_key":"","name":"1.2TB [781518-B21]","full_name":"HP 1.2TB [781518-B21]","name_prefix":"Жесткий диск","extended_name":"Жесткий диск HP 1.2TB [781518-B21]","status":"active","images":{"header":"https:\/\/imgproxy.onliner.by\/vBlLl-nXdpwSYKyToa0COXhdgeWapErG6Ey1u9Fnip8\/w:170\/h:250\/z:2\/f:jpg\/aHR0cHM6Ly9jb250\/ZW50Lm9ubGluZXIu\/YnkvY2F0YWxvZy9k\/ZXZpY2Uvb3JpZ2lu\/YWwvMzkwZDNhOGQ1\/MGZmYmUxNDIyYWVm\/YTQ3YjRlNTRjMWIu\/anBn"},"description":"2.5\", SAS 3.0 (12Gbps), 10000 об\/мин","description_list":["2.5\"","SAS 3.0 (12Gbps)","10000 об\/мин"],"micro_description":"2.5\", SAS 3.0 (12Gbps), 10000 об\/мин","micro_description_list":["2.5\"","SAS 3.0 (12Gbps)","10000 об\/мин"],"html_url":"https:\/\/catalog.onliner.by\/hdd\/hp\/781518b21","reviews":{"rating":0,"count":0,"html_url":"https:\/\/catalog.onliner.by\/hdd\/hp\/781518b21\/reviews","url":"https:\/\/catalog.api.onliner.by\/products\/781518b21\/reviews"},"review_url":null,"color_code":null,"prices":{"price_min":{"amount":"867.10","currency":"BYN","converted":{"BYN":{"amount":"867.10","currency":"BYN"}}},"price_max":{"amount":"867.10","currency":"BYN","converted":{"BYN":{"amount":"867.10","currency":"BYN"}}},"offers":{"count":1},"html_url":"https:\/\/catalog.onliner.by\/hdd\/hp\/781518b21\/prices","url":"https:\/\/shop.api.onliner.by\/products\/781518b21\/positions"},"max_installment_terms":null,"max_cobrand_cashback":null,"sale":{"is_on_sale":false,"discount":0,"min_prices_median":{"amount":"927.04","currency":"BYN"},"subscribed":false,"can_be_subscribed":true},"second":{"offers_count":0,"min_price":null,"max_price":null},"forum":{"topic_id":null,"topic_url":null,"post_url":"https:\/\/forum.onliner.by\/posting.php?mode=newtopic&f=148&device=781518b21","replies_count":null},"url":"https:\/\/catalog.api.onliner.by\/products\/781518b21","advertise":null,"stickers":null,"prime_info":{"available":false},"in_bookmarks":false,"by_parts_info":null}],"total_ungrouped":953,"meta":{"html_url":"https:\/\/catalog.onliner.by\/hdd?group=0&group_limit=1"},"total":953,"page":{"limit":30,"items":30,"current":10,"last":32}}